folerHandle/__init__.py
folerHandle/demo.py
folerHandle/dictPrint.py
folerHandle/folderAnalysis.py
folerhandle-1.2.dist-info/LICENSE
folerhandle-1.2.dist-info/METADATA
folerhandle-1.2.dist-info/WHEEL
folerhandle-1.2.dist-info/top_level.txt
folerhandle-1.2.dist-info/RECORD
